{"protocol":{"minReaderVersion":1,"minWriterVersion":2}}
{"metaData":{"id":"70d6138b-fa36-4274-814f-2438067d3f43","format":{"provider":"parquet","options":{}},"schemaString":"{\"type\":\"struct\",\"fields\":[{\"name\":\"GameId\",\"type\":\"integer\",\"nullable\":true,\"metadata\":{}},{\"name\":\"RoundId\",\"type\":\"integer\",\"nullable\":true,\"metadata\":{}},{\"name\":\"Season\",\"type\":\"integer\",\"nullable\":true,\"metadata\":{}},{\"name\":\"SeasonType\",\"type\":\"integer\",\"nullable\":true,\"metadata\":{}},{\"name\":\"Group\",\"type\":\"string\",\"nullable\":true,\"metadata\":{}},{\"name\":\"TeamAId\",\"type\":\"integer\",\"nullable\":true,\"metadata\":{}},{\"name\":\"TeamBId\",\"type\":\"integer\",\"nullable\":true,\"metadata\":{}},{\"name\":\"VenueId\",\"type\":\"integer\",\"nullable\":true,\"metadata\":{}},{\"name\":\"Day\",\"type\":\"string\",\"nullable\":true,\"metadata\":{}},{\"name\":\"DateTime\",\"type\":\"string\",\"nullable\":true,\"metadata\":{}},{\"name\":\"Status\",\"type\":\"string\",\"nullable\":true,\"metadata\":{}},{\"name\":\"Week\",\"type\":\"integer\",\"nullable\":true,\"metadata\":{}},{\"name\":\"BestOf\",\"type\":\"string\",\"nullable\":true,\"metadata\":{}},{\"name\":\"Winner\",\"type\":\"string\",\"nullable\":true,\"metadata\":{}},{\"name\":\"VenueType\",\"type\":\"string\",\"nullable\":true,\"metadata\":{}},{\"name\":\"TeamAKey\",\"type\":\"string\",\"nullable\":true,\"metadata\":{}},{\"name\":\"TeamAName\",\"type\":\"string\",\"nullable\":true,\"metadata\":{}},{\"name\":\"TeamAScore\",\"type\":\"integer\",\"nullable\":true,\"metadata\":{}},{\"name\":\"TeamBKey\",\"type\":\"string\",\"nullable\":true,\"metadata\":{}},{\"name\":\"TeamBName\",\"type\":\"string\",\"nullable\":true,\"metadata\":{}},{\"name\":\"TeamBScore\",\"type\":\"integer\",\"nullable\":true,\"metadata\":{}},{\"name\":\"TeamAMoneyLine\",\"type\":\"integer\",\"nullable\":true,\"metadata\":{}},{\"name\":\"TeamBMoneyLine\",\"type\":\"integer\",\"nullable\":true,\"metadata\":{}},{\"name\":\"DrawMoneyLine\",\"type\":\"integer\",\"nullable\":true,\"metadata\":{}},{\"name\":\"PointSpread\",\"type\":\"decimal(10,0)\",\"nullable\":true,\"metadata\":{}},{\"name\":\"TeamAPointSpreadPayout\",\"type\":\"integer\",\"nullable\":true,\"metadata\":{}},{\"name\":\"TeamBPointSpreadPayout\",\"type\":\"integer\",\"nullable\":true,\"metadata\":{}},{\"name\":\"Updated\",\"type\":\"string\",\"nullable\":true,\"metadata\":{}},{\"name\":\"UpdatedUtc\",\"type\":\"string\",\"nullable\":true,\"metadata\":{}},{\"name\":\"IsClosed\",\"type\":\"boolean\",\"nullable\":true,\"metadata\":{}}]}","partitionColumns":[],"configuration":{},"createdTime":1667277873960}}
{"add":{"path":"part-00000-4e08497a-47e5-4ef7-a227-0c6e92b406ad-c000.snappy.parquet","partitionValues":{},"size":10238,"modificationTime":1667277877973,"dataChange":true,"stats":"{\"numRecords\":30,\"minValues\":{\"GameId\":100015581,\"RoundId\":100002639,\"Season\":2022,\"SeasonType\":1,\"Group\":\"Group D\",\"TeamAId\":100000081,\"TeamBId\":100000081,\"Day\":\"2022-09-22T00:00:00\",\"DateTime\":\"2022-09-22T10:30:00\",\"Status\":\"Final\",\"BestOf\":\"3\",\"Winner\":\"Scrambled\",\"TeamAKey\":\"00N\",\"TeamAName\":\"00Nation\",\"TeamAScore\":0,\"TeamBKey\":\"00N\",\"TeamBName\":\"00Nation\",\"TeamBScore\":0,\"Updated\":\"2022-09-22T08:56:23\",\"UpdatedUtc\":\"2022-09-22T12:56:23\"},\"maxValues\":{\"GameId\":100015753,\"RoundId\":100002663,\"Season\":2022,\"SeasonType\":3,\"Group\":\"Group D\",\"TeamAId\":100000531,\"TeamBId\":100000531,\"Day\":\"2022-10-23T00:00:00\",\"DateTime\":\"2022-10-23T20:30:00\",\"Status\":\"Scheduled\",\"BestOf\":\"5\",\"Winner\":\"Scrambled\",\"TeamAKey\":\"VIT\",\"TeamAName\":\"mousesports\",\"TeamAScore\":5,\"TeamBKey\":\"VTX\",\"TeamBName\":\"compLexity\",\"TeamBScore\":8,\"Updated\":\"2022-10-22T19:13:34\",\"UpdatedUtc\":\"2022-10-22T23:13:34\"},\"nullCount\":{\"GameId\":0,\"RoundId\":0,\"Season\":0,\"SeasonType\":0,\"Group\":18,\"TeamAId\":0,\"TeamBId\":0,\"VenueId\":30,\"Day\":0,\"DateTime\":0,\"Status\":0,\"Week\":30,\"BestOf\":0,\"Winner\":0,\"VenueType\":30,\"TeamAKey\":0,\"TeamAName\":0,\"TeamAScore\":1,\"TeamBKey\":0,\"TeamBName\":0,\"TeamBScore\":1,\"TeamAMoneyLine\":30,\"TeamBMoneyLine\":30,\"DrawMoneyLine\":30,\"PointSpread\":30,\"TeamAPointSpreadPayout\":30,\"TeamBPointSpreadPayout\":30,\"Updated\":0,\"UpdatedUtc\":0,\"IsClosed\":0}}"}}
{"commitInfo":{"timestamp":1667277879105,"operation":"CREATE OR REPLACE TABLE AS SELECT","operationParameters":{"isManaged":"true","description":null,"partitionBy":"[]","properties":"{}"},"isolationLevel":"Serializable","isBlindAppend":false,"operationMetrics":{"numFiles":"1","numOutputRows":"30","numOutputBytes":"10238"},"engineInfo":"Apache-Spark/3.2.2 Delta-Lake/2.0.0","txnId":"125ec02d-24fd-4a09-8106-0a3983bfeec8"}}
